pum/__init__.py
pum/changelog.py
pum/checker.py
pum/cli.py
pum/config_model.py
pum/connection.py
pum/dependency_handler.py
pum/dumper.py
pum/exceptions.py
pum/feedback.py
pum/hook.py
pum/info.py
pum/parameter.py
pum/pum_config.py
pum/report_generator.py
pum/role_manager.py
pum/schema_migrations.py
pum/sql_content.py
pum/upgrader.py
pum-1.3.2.dist-info/licenses/LICENSE
pum-1.3.2.dist-info/METADATA
pum-1.3.2.dist-info/WHEEL
pum-1.3.2.dist-info/entry_points.txt
pum-1.3.2.dist-info/top_level.txt
pum-1.3.2.dist-info/RECORD
